DjangoShejimoshiYuZuijiaShijian/README.md
DjangoShejimoshiYuZuijiaShijian/__init__.py
DjangoShejimoshiYuZuijiaShijian/__main__.py
DjangoShejimoshiYuZuijiaShijian/file.epub
DjangoShejimoshiYuZuijiaShijian/index.html
DjangoShejimoshiYuZuijiaShijian/css/__init__.py
DjangoShejimoshiYuZuijiaShijian/css/annotations.css
DjangoShejimoshiYuZuijiaShijian/css/main.css
DjangoShejimoshiYuZuijiaShijian/css/normalize.css
DjangoShejimoshiYuZuijiaShijian/css/popup.css
DjangoShejimoshiYuZuijiaShijian/font/__init__.py
DjangoShejimoshiYuZuijiaShijian/font/fontello.eot
DjangoShejimoshiYuZuijiaShijian/font/fontello.svg
DjangoShejimoshiYuZuijiaShijian/font/fontello.ttf
DjangoShejimoshiYuZuijiaShijian/font/fontello.woff
DjangoShejimoshiYuZuijiaShijian/img/__init__.py
DjangoShejimoshiYuZuijiaShijian/img/annotator-glyph-sprite.png
DjangoShejimoshiYuZuijiaShijian/img/annotator-icon-sprite.png
DjangoShejimoshiYuZuijiaShijian/img/apple-touch-icon.png
DjangoShejimoshiYuZuijiaShijian/img/cancelfullscreen.png
DjangoShejimoshiYuZuijiaShijian/img/close.png
DjangoShejimoshiYuZuijiaShijian/img/fullscreen.png
DjangoShejimoshiYuZuijiaShijian/img/loader.gif
DjangoShejimoshiYuZuijiaShijian/img/menu-icon.png
DjangoShejimoshiYuZuijiaShijian/img/save.png
DjangoShejimoshiYuZuijiaShijian/img/saved.png
DjangoShejimoshiYuZuijiaShijian/img/settings-s.png
DjangoShejimoshiYuZuijiaShijian/img/settings.png
DjangoShejimoshiYuZuijiaShijian/img/star.png
DjangoShejimoshiYuZuijiaShijian/js/__init__.py
DjangoShejimoshiYuZuijiaShijian/js/epub.js
DjangoShejimoshiYuZuijiaShijian/js/epub.min.js
DjangoShejimoshiYuZuijiaShijian/js/epub.min.map
DjangoShejimoshiYuZuijiaShijian/js/hooks.min.js
DjangoShejimoshiYuZuijiaShijian/js/hooks.min.map
DjangoShejimoshiYuZuijiaShijian/js/reader.js
DjangoShejimoshiYuZuijiaShijian/js/reader.js.map
DjangoShejimoshiYuZuijiaShijian/js/reader.min.js
DjangoShejimoshiYuZuijiaShijian/js/reader.min.map
DjangoShejimoshiYuZuijiaShijian/js/hooks/__init__.py
django_shejimoshi_yu_zuijia_shijian-2024.3.1.0.dist-info/METADATA
django_shejimoshi_yu_zuijia_shijian-2024.3.1.0.dist-info/WHEEL
django_shejimoshi_yu_zuijia_shijian-2024.3.1.0.dist-info/entry_points.txt
django_shejimoshi_yu_zuijia_shijian-2024.3.1.0.dist-info/top_level.txt
django_shejimoshi_yu_zuijia_shijian-2024.3.1.0.dist-info/RECORD
